{
  "steamid": "76561199689200539",
  "country": "ru",
  "cached_at": "2026-07-01T13:58:43.710Z",
  "user": {},
  "maps": {
    "header": {
      "title": "april18",
      "avatar": "https://avatars.steamstatic.com/61ad2272702ec63ee7e4285b8d66b2eda3bb7212_full.jpg",
      "desc": {
        "{{Points}}": 21204,
        "{{Position}}": 39,
        "{{COMPLETIONS-MAP}}": "141 (84.94%)"
      }
    },
    "list": [
      {
        "map": "kz_mazemerized",
        "points": "226.5626",
        "time_record": "08:30.6250",
        "unixtime_record": 1780483631,
        "place_num": "17 / 97",
        "tier": "7",
        "completions": "8"
      },
      {
        "map": "kz_dojo",
        "points": "154.7610",
        "time_record": "04:02.6250",
        "unixtime_record": 1781277700,
        "place_num": "19 / 1 467",
        "tier": "3",
        "completions": "4"
      },
      {
        "map": "skz_bananaysoda_2",
        "points": "261.6288",
        "time_record": "02:40.6563",
        "unixtime_record": 1780501030,
        "place_num": "23 / 752",
        "tier": "5",
        "completions": "13"
      },
      {
        "map": "kz_drunkards",
        "points": "70.0417",
        "time_record": "12:24.6875",
        "unixtime_record": 1780573816,
        "place_num": "23 / 51",
        "tier": "6",
        "completions": "2"
      },
      {
        "map": "kz_chloroplast",
        "points": "271.6315",
        "time_record": "02:12.3282",
        "unixtime_record": 1780152719,
        "place_num": "27 / 247",
        "tier": "6",
        "completions": "15"
      },
      {
        "map": "kz_alien_city",
        "points": "292.1508",
        "time_record": "07:53.7500",
        "unixtime_record": 1781014576,
        "place_num": "27 / 362",
        "tier": "6",
        "completions": "23"
      },
      {
        "map": "kz_psychosomatic",
        "points": "192.3219",
        "time_record": "06:41.1094",
        "unixtime_record": 1780408953,
        "place_num": "27 / 99",
        "tier": "6",
        "completions": "16"
      },
      {
        "map": "kz_jakke",
        "points": "211.7969",
        "time_record": "15:39.1250",
        "unixtime_record": 1780238520,
        "place_num": "28 / 265",
        "tier": "5",
        "completions": "2"
      },
      {
        "map": "kz_sillychicken",
        "points": "228.4564",
        "time_record": "02:02.2344",
        "unixtime_record": 1781370760,
        "place_num": "28 / 1 055",
        "tier": "4",
        "completions": "9"
      },
      {
        "map": "kz_valley",
        "points": "140.7672",
        "time_record": "00:39.7657",
        "unixtime_record": 1752676316,
        "place_num": "31 / 20 318",
        "tier": "2",
        "completions": "31"
      },
      {
        "map": "kzpro_only_up_extended",
        "points": "128.5660",
        "time_record": "03:43.9844",
        "unixtime_record": 1752675745,
        "place_num": "31 / 29 282",
        "tier": "3",
        "completions": "14"
      },
      {
        "map": "kz_afterlife",
        "points": "260.7598",
        "time_record": "03:29.4844",
        "unixtime_record": 1780499855,
        "place_num": "35 / 488",
        "tier": "6",
        "completions": "13"
      },
      {
        "map": "kz_sxb2_remake",
        "points": "246.8815",
        "time_record": "03:17.7813",
        "unixtime_record": 1780502857,
        "place_num": "35 / 1 510",
        "tier": "4",
        "completions": "26"
      },
      {
        "map": "kz_cf_foliage",
        "points": "151.8991",
        "time_record": "13:28.9532",
        "unixtime_record": 1780655637,
        "place_num": "36 / 85",
        "tier": "7",
        "completions": "5"
      },
      {
        "map": "kz_fastcombowombo_v2",
        "points": "137.7192",
        "time_record": "02:26.8750",
        "unixtime_record": 1780136756,
        "place_num": "38 / 369",
        "tier": "3",
        "completions": "5"
      },
      {
        "map": "kz_kukkojapallokidutus",
        "points": "196.5082",
        "time_record": "03:51.8750",
        "unixtime_record": 1781103520,
        "place_num": "40 / 233",
        "tier": "6",
        "completions": "12"
      },
      {
        "map": "kz_mess",
        "points": "194.1455",
        "time_record": "05:21.1875",
        "unixtime_record": 1781214191,
        "place_num": "41 / 323",
        "tier": "5",
        "completions": "5"
      },
      {
        "map": "kz_ggsh",
        "points": "252.3181",
        "time_record": "04:28.3438",
        "unixtime_record": 1780563301,
        "place_num": "43 / 488",
        "tier": "6",
        "completions": "22"
      },
      {
        "map": "kz_kzro_hardhoodoo",
        "points": "137.6466",
        "time_record": "52:09.9375",
        "unixtime_record": 1773174154,
        "place_num": "43 / 108",
        "tier": "6",
        "completions": "2"
      },
      {
        "map": "kz_ehcivec_final",
        "points": "184.0511",
        "time_record": "01:41.5782",
        "unixtime_record": 1757052237,
        "place_num": "46 / 6 940",
        "tier": "3",
        "completions": "34"
      },
      {
        "map": "kz_retribution_v2_final",
        "points": "284.8858",
        "time_record": "06:20.2188",
        "unixtime_record": 1775981269,
        "place_num": "46 / 558",
        "tier": "6",
        "completions": "11"
      },
      {
        "map": "kz_ladderhell",
        "points": "162.3868",
        "time_record": "03:02.7032",
        "unixtime_record": 1764317800,
        "place_num": "50 / 859",
        "tier": "4",
        "completions": "20"
      },
      {
        "map": "kz_lionheart",
        "points": "291.9511",
        "time_record": "06:07.2344",
        "unixtime_record": 1780577423,
        "place_num": "52 / 642",
        "tier": "6",
        "completions": "29"
      },
      {
        "map": "kz_dyd_ladderjumps",
        "points": "217.5424",
        "time_record": "00:41.7344",
        "unixtime_record": 1772113237,
        "place_num": "52 / 1 092",
        "tier": "4",
        "completions": "6"
      },
      {
        "map": "kz_fastmap",
        "points": "138.8891",
        "time_record": "00:52.1719",
        "unixtime_record": 1754769314,
        "place_num": "55 / 12 792",
        "tier": "2",
        "completions": "5"
      },
      {
        "map": "kz_mescaline_f",
        "points": "236.0640",
        "time_record": "01:02.4219",
        "unixtime_record": 1771245602,
        "place_num": "56 / 1 318",
        "tier": "4",
        "completions": "8"
      },
      {
        "map": "kz_kiwi_hym",
        "points": "35.4750",
        "time_record": "58:13.4532",
        "unixtime_record": 1781016344,
        "place_num": "58 / 82",
        "tier": "8",
        "completions": "2"
      },
      {
        "map": "kz_antharas",
        "points": "203.0604",
        "time_record": "05:05.5000",
        "unixtime_record": 1780154824,
        "place_num": "62 / 1 692",
        "tier": "5",
        "completions": "34"
      },
      {
        "map": "kz_why",
        "points": "243.4597",
        "time_record": "01:07.8125",
        "unixtime_record": 1780132516,
        "place_num": "64 / 1 337",
        "tier": "4",
        "completions": "3"
      },
      {
        "map": "kz_pendulum",
        "points": "148.5121",
        "time_record": "16:16.2032",
        "unixtime_record": 1780570940,
        "place_num": "64 / 189",
        "tier": "6",
        "completions": "4"
      },
      {
        "map": "kz_kiwitech",
        "points": "143.7938",
        "time_record": "02:18.2344",
        "unixtime_record": 1764315060,
        "place_num": "65 / 777",
        "tier": "5",
        "completions": "6"
      },
      {
        "map": "kz_insomnia",
        "points": "182.3538",
        "time_record": "04:27.3282",
        "unixtime_record": 1780134480,
        "place_num": "69 / 992",
        "tier": "4",
        "completions": "4"
      },
      {
        "map": "kz_unmake",
        "points": "158.7191",
        "time_record": "28:38.9063",
        "unixtime_record": 1780492000,
        "place_num": "69 / 150",
        "tier": "7",
        "completions": "21"
      },
      {
        "map": "kz_otakuroom_v3",
        "points": "186.2428",
        "time_record": "13:04.3438",
        "unixtime_record": 1754767855,
        "place_num": "70 / 6 815",
        "tier": "3",
        "completions": "2"
      },
      {
        "map": "kz_custos",
        "points": "168.7712",
        "time_record": "03:39.2813",
        "unixtime_record": 1771937184,
        "place_num": "75 / 647",
        "tier": "5",
        "completions": "10"
      },
      {
        "map": "kz_spacemario_h",
        "points": "265.0607",
        "time_record": "12:59.2188",
        "unixtime_record": 1780424243,
        "place_num": "75 / 882",
        "tier": "6",
        "completions": "22"
      },
      {
        "map": "kz_alouette_fix",
        "points": "150.4930",
        "time_record": "04:56.3438",
        "unixtime_record": 1756016322,
        "place_num": "77 / 4 953",
        "tier": "3",
        "completions": "4"
      },
      {
        "map": "kz_oloramasa",
        "points": "220.0252",
        "time_record": "06:08.6719",
        "unixtime_record": 1781104637,
        "place_num": "77 / 402",
        "tier": "6",
        "completions": "9"
      },
      {
        "map": "kz_madhatter",
        "points": "191.3645",
        "time_record": "01:17.1719",
        "unixtime_record": 1780145352,
        "place_num": "78 / 3 833",
        "tier": "3",
        "completions": "6"
      },
      {
        "map": "kz_blackness",
        "points": "152.1210",
        "time_record": "06:11.8750",
        "unixtime_record": 1775629534,
        "place_num": "80 / 278",
        "tier": "6",
        "completions": "7"
      },
      {
        "map": "kz_kiwiexultation",
        "points": "48.1968",
        "time_record": "17:40.9532",
        "unixtime_record": 1779808592,
        "place_num": "82 / 117",
        "tier": "6",
        "completions": "3"
      },
      {
        "map": "kz_antimony",
        "points": "188.2353",
        "time_record": "05:48.8907",
        "unixtime_record": 1780405819,
        "place_num": "82 / 1 201",
        "tier": "4",
        "completions": "5"
      },
      {
        "map": "kz_nightcastle",
        "points": "179.5276",
        "time_record": "01:24.1875",
        "unixtime_record": 1771416619,
        "place_num": "82 / 1 342",
        "tier": "4",
        "completions": "15"
      },
      {
        "map": "kz_skytower",
        "points": "207.2415",
        "time_record": "09:43.2657",
        "unixtime_record": 1762257507,
        "place_num": "83 / 24 388",
        "tier": "3",
        "completions": "16"
      },
      {
        "map": "kz_key",
        "points": "131.1864",
        "time_record": "02:35.3594",
        "unixtime_record": 1771672378,
        "place_num": "86 / 13 922",
        "tier": "2",
        "completions": "4"
      },
      {
        "map": "kz_futureblock",
        "points": "143.8754",
        "time_record": "02:33.1094",
        "unixtime_record": 1752920572,
        "place_num": "89 / 5 291",
        "tier": "3",
        "completions": "11"
      },
      {
        "map": "kz_kiwiqualia",
        "points": "164.9267",
        "time_record": "07:06.4532",
        "unixtime_record": 1775630648,
        "place_num": "90 / 564",
        "tier": "5",
        "completions": "10"
      },
      {
        "map": "kz_slowrun",
        "points": "132.7527",
        "time_record": "03:35.6563",
        "unixtime_record": 1780153711,
        "place_num": "92 / 406",
        "tier": "6",
        "completions": "10"
      },
      {
        "map": "kz_alfie",
        "points": "177.2064",
        "time_record": "02:38.2500",
        "unixtime_record": 1770890521,
        "place_num": "94 / 588",
        "tier": "5",
        "completions": "11"
      },
      {
        "map": "kz_maga",
        "points": "68.3132",
        "time_record": "11:01.3907",
        "unixtime_record": 1772279014,
        "place_num": "94 / 190",
        "tier": "6",
        "completions": "1"
      },
      {
        "map": "kz_epiphany_v2",
        "points": "236.9037",
        "time_record": "04:53.3594",
        "unixtime_record": 1771238081,
        "place_num": "95 / 1 424",
        "tier": "5",
        "completions": "8"
      },
      {
        "map": "kz_hitech",
        "points": "199.8160",
        "time_record": "04:24.2657",
        "unixtime_record": 1780564890,
        "place_num": "96 / 539",
        "tier": "5",
        "completions": "7"
      },
      {
        "map": "kz_divert",
        "points": "107.6682",
        "time_record": "09:20.5157",
        "unixtime_record": 1780486696,
        "place_num": "97 / 225",
        "tier": "6",
        "completions": "3"
      },
      {
        "map": "kz_monstrosity",
        "points": "64.5926",
        "time_record": "14:52.9532",
        "unixtime_record": 1772200858,
        "place_num": "97 / 178",
        "tier": "6",
        "completions": "2"
      },
      {
        "map": "kz_okaychamp",
        "points": "185.7674",
        "time_record": "03:19.2188",
        "unixtime_record": 1781272087,
        "place_num": "98 / 1 672",
        "tier": "5",
        "completions": "10"
      },
      {
        "map": "kz_kuutio",
        "points": "180.6543",
        "time_record": "05:00.2813",
        "unixtime_record": 1771323272,
        "place_num": "100 / 1 755",
        "tier": "3",
        "completions": "2"
      },
      {
        "map": "kz_slide_deee",
        "points": "41.7158",
        "time_record": "38:12.1407",
        "unixtime_record": 1774463061,
        "place_num": "101 / 131",
        "tier": "6",
        "completions": "1"
      },
      {
        "map": "kz_hoist",
        "points": "130.4133",
        "time_record": "03:03.0000",
        "unixtime_record": 1779985365,
        "place_num": "103 / 398",
        "tier": "5",
        "completions": "2"
      },
      {
        "map": "kz_2fast",
        "points": "166.2895",
        "time_record": "00:58.3594",
        "unixtime_record": 1771673296,
        "place_num": "103 / 2 465",
        "tier": "3",
        "completions": "7"
      },
      {
        "map": "kz_rectangle",
        "points": "173.4099",
        "time_record": "01:04.2344",
        "unixtime_record": 1771325005,
        "place_num": "106 / 1 272",
        "tier": "4",
        "completions": "11"
      },
      {
        "map": "kz_itz_updown",
        "points": "191.2380",
        "time_record": "03:34.7032",
        "unixtime_record": 1767116158,
        "place_num": "110 / 891",
        "tier": "4",
        "completions": "15"
      },
      {
        "map": "kz_mandelbrot",
        "points": "208.1718",
        "time_record": "02:42.4688",
        "unixtime_record": 1771324047,
        "place_num": "113 / 1 853",
        "tier": "4",
        "completions": "6"
      },
      {
        "map": "kz_longjumps_space",
        "points": "240.0653",
        "time_record": "01:51.1875",
        "unixtime_record": 1780503416,
        "place_num": "116 / 3 860",
        "tier": "4",
        "completions": "18"
      },
      {
        "map": "kz_sanctum",
        "points": "165.3054",
        "time_record": "02:26.2344",
        "unixtime_record": 1780580897,
        "place_num": "124 / 1 596",
        "tier": "3",
        "completions": "3"
      },
      {
        "map": "kz_16pillars",
        "points": "107.1852",
        "time_record": "08:44.5782",
        "unixtime_record": 1751574648,
        "place_num": "125 / 8 518",
        "tier": "2",
        "completions": "6"
      },
      {
        "map": "kz_demonhours",
        "points": "219.6342",
        "time_record": "01:44.8438",
        "unixtime_record": 1781371259,
        "place_num": "128 / 1 452",
        "tier": "5",
        "completions": "17"
      },
      {
        "map": "kz_dethroned",
        "points": "95.1973",
        "time_record": "06:00.4532",
        "unixtime_record": 1756052803,
        "place_num": "134 / 455",
        "tier": "5",
        "completions": "3"
      },
      {
        "map": "kz_bigcastle",
        "points": "88.5060",
        "time_record": "03:38.2344",
        "unixtime_record": 1774512073,
        "place_num": "134 / 1 668",
        "tier": "3",
        "completions": "7"
      },
      {
        "map": "kz_slide_era",
        "points": "91.5873",
        "time_record": "07:20.2657",
        "unixtime_record": 1780653519,
        "place_num": "135 / 482",
        "tier": "5",
        "completions": "7"
      },
      {
        "map": "kz_kzro_mountainroad",
        "points": "278.4279",
        "time_record": "03:34.2032",
        "unixtime_record": 1780323501,
        "place_num": "137 / 959",
        "tier": "5",
        "completions": "5"
      },
      {
        "map": "kz_luv_less",
        "points": "223.6162",
        "time_record": "03:50.8282",
        "unixtime_record": 1780576214,
        "place_num": "138 / 2 970",
        "tier": "4",
        "completions": "15"
      },
      {
        "map": "kz_persona_is_a_furry",
        "points": "199.9920",
        "time_record": "05:19.7657",
        "unixtime_record": 1767118902,
        "place_num": "139 / 822",
        "tier": "5",
        "completions": "4"
      },
      {
        "map": "kz_bluekarko",
        "points": "140.6579",
        "time_record": "04:09.5469",
        "unixtime_record": 1780579453,
        "place_num": "145 / 1 144",
        "tier": "3",
        "completions": "3"
      },
      {
        "map": "kz_serfdom",
        "points": "94.9185",
        "time_record": "01:11.4063",
        "unixtime_record": 1771950684,
        "place_num": "146 / 5 607",
        "tier": "2",
        "completions": "7"
      },
      {
        "map": "kz_devon",
        "points": "183.9984",
        "time_record": "01:52.2657",
        "unixtime_record": 1780142766,
        "place_num": "146 / 3 101",
        "tier": "3",
        "completions": "3"
      },
      {
        "map": "kz_amber_od",
        "points": "186.8523",
        "time_record": "00:49.7969",
        "unixtime_record": 1751730333,
        "place_num": "147 / 2 630",
        "tier": "3",
        "completions": "29"
      },
      {
        "map": "kz_spiritblockv2",
        "points": "106.9885",
        "time_record": "01:32.9532",
        "unixtime_record": 1752764345,
        "place_num": "152 / 13 343",
        "tier": "2",
        "completions": "11"
      },
      {
        "map": "kz_old_depression",
        "points": "153.0772",
        "time_record": "03:20.0469",
        "unixtime_record": 1771326374,
        "place_num": "154 / 1 039",
        "tier": "4",
        "completions": "4"
      },
      {
        "map": "bkz_evanstep",
        "points": "113.5413",
        "time_record": "03:34.7500",
        "unixtime_record": 1770808900,
        "place_num": "154 / 832",
        "tier": "4",
        "completions": "4"
      },
      {
        "map": "kz_opus",
        "points": "106.1468",
        "time_record": "01:37.2188",
        "unixtime_record": 1749227933,
        "place_num": "157 / 10 144",
        "tier": "2",
        "completions": "18"
      },
      {
        "map": "kz_zoomer_fix",
        "points": "186.7963",
        "time_record": "03:45.5000",
        "unixtime_record": 1770808192,
        "place_num": "168 / 2 173",
        "tier": "4",
        "completions": "7"
      },
      {
        "map": "kz_maze",
        "points": "115.1755",
        "time_record": "03:09.5157",
        "unixtime_record": 1781273042,
        "place_num": "172 / 2 954",
        "tier": "2",
        "completions": "2"
      },
      {
        "map": "kz_loftroofs",
        "points": "172.7692",
        "time_record": "04:56.0000",
        "unixtime_record": 1751224383,
        "place_num": "177 / 5 042",
        "tier": "3",
        "completions": "9"
      },
      {
        "map": "kz_kzro_syotiles",
        "points": "122.7558",
        "time_record": "01:07.3282",
        "unixtime_record": 1746216585,
        "place_num": "189 / 42 354",
        "tier": "2",
        "completions": "18"
      },
      {
        "map": "kz_alice_fix",
        "points": "201.4077",
        "time_record": "01:07.4375",
        "unixtime_record": 1756035078,
        "place_num": "189 / 3 236",
        "tier": "4",
        "completions": "21"
      },
      {
        "map": "kz_blockhardy2k",
        "points": "173.6866",
        "time_record": "01:55.9063",
        "unixtime_record": 1751885279,
        "place_num": "192 / 4 010",
        "tier": "3",
        "completions": "13"
      },
      {
        "map": "kz_wasabi",
        "points": "107.1316",
        "time_record": "01:39.0157",
        "unixtime_record": 1753246337,
        "place_num": "197 / 10 874",
        "tier": "2",
        "completions": "7"
      },
      {
        "map": "kz_kiwitown",
        "points": "106.9626",
        "time_record": "09:16.4532",
        "unixtime_record": 1780649955,
        "place_num": "202 / 2 388",
        "tier": "2",
        "completions": "1"
      },
      {
        "map": "kz_niche",
        "points": "172.1841",
        "time_record": "03:53.8750",
        "unixtime_record": 1751732859,
        "place_num": "204 / 26 525",
        "tier": "3",
        "completions": "8"
      },
      {
        "map": "kz_kiwi_lars",
        "points": "188.1751",
        "time_record": "03:50.4844",
        "unixtime_record": 1781493045,
        "place_num": "209 / 1 798",
        "tier": "4",
        "completions": "7"
      },
      {
        "map": "kz_sunstone",
        "points": "108.4215",
        "time_record": "02:05.3438",
        "unixtime_record": 1751569500,
        "place_num": "214 / 11 840",
        "tier": "2",
        "completions": "8"
      },
      {
        "map": "kz_labour",
        "points": "158.3137",
        "time_record": "02:02.9375",
        "unixtime_record": 1767131128,
        "place_num": "216 / 5 401",
        "tier": "3",
        "completions": "4"
      },
      {
        "map": "kz_shift",
        "points": "150.4481",
        "time_record": "01:52.4375",
        "unixtime_record": 1780651225,
        "place_num": "219 / 1 896",
        "tier": "3",
        "completions": "2"
      },
      {
        "map": "kz_brightblock",
        "points": "52.8005",
        "time_record": "02:03.5938",
        "unixtime_record": 1753649613,
        "place_num": "219 / 16 349",
        "tier": "1",
        "completions": "3"
      },
      {
        "map": "kz_adv_cursedjourney",
        "points": "138.4062",
        "time_record": "51:40.5938",
        "unixtime_record": 1754396869,
        "place_num": "220 / 985",
        "tier": "4",
        "completions": "1"
      },
      {
        "map": "kz_sp1_behold",
        "points": "111.5534",
        "time_record": "04:27.8282",
        "unixtime_record": 1754494176,
        "place_num": "226 / 1 342",
        "tier": "3",
        "completions": "2"
      },
      {
        "map": "kz_combobreaker",
        "points": "113.7434",
        "time_record": "01:38.6250",
        "unixtime_record": 1746436389,
        "place_num": "231 / 14 921",
        "tier": "2",
        "completions": "17"
      },
      {
        "map": "kz_leviathan",
        "points": "131.4426",
        "time_record": "06:05.8750",
        "unixtime_record": 1767095384,
        "place_num": "240 / 3 301",
        "tier": "3",
        "completions": "2"
      },
      {
        "map": "kz_grotto",
        "points": "118.0496",
        "time_record": "01:34.5625",
        "unixtime_record": 1751982621,
        "place_num": "241 / 35 221",
        "tier": "2",
        "completions": "13"
      },
      {
        "map": "kz_aether_fix",
        "points": "119.1063",
        "time_record": "05:13.3125",
        "unixtime_record": 1757252017,
        "place_num": "243 / 733",
        "tier": "5",
        "completions": "3"
      },
      {
        "map": "kz_kiwibridge",
        "points": "68.6165",
        "time_record": "01:04.0313",
        "unixtime_record": 1780649299,
        "place_num": "245 / 26 930",
        "tier": "1",
        "completions": "3"
      },
      {
        "map": "kz_hex",
        "points": "175.5836",
        "time_record": "01:32.5625",
        "unixtime_record": 1780142122,
        "place_num": "255 / 2 693",
        "tier": "3",
        "completions": "4"
      },
      {
        "map": "kz_spire",
        "points": "96.5802",
        "time_record": "06:39.2032",
        "unixtime_record": 1754477115,
        "place_num": "264 / 10 853",
        "tier": "2",
        "completions": "3"
      },
      {
        "map": "kz_cheese",
        "points": "114.8084",
        "time_record": "01:46.0313",
        "unixtime_record": 1753014643,
        "place_num": "270 / 8 776",
        "tier": "2",
        "completions": "4"
      },
      {
        "map": "kz_communityjump3",
        "points": "178.2076",
        "time_record": "34:21.2500",
        "unixtime_record": 1752674886,
        "place_num": "271 / 2 178",
        "tier": "4",
        "completions": "8"
      },
      {
        "map": "kz_igneous",
        "points": "198.5273",
        "time_record": "01:49.0157",
        "unixtime_record": 1752666145,
        "place_num": "272 / 45 419",
        "tier": "3",
        "completions": "22"
      },
      {
        "map": "kz_lust",
        "points": "117.6944",
        "time_record": "00:56.0157",
        "unixtime_record": 1771704802,
        "place_num": "293 / 9 682",
        "tier": "2",
        "completions": "26"
      },
      {
        "map": "kz_after_agitation_v2",
        "points": "98.4975",
        "time_record": "26:03.0313",
        "unixtime_record": 1753248815,
        "place_num": "296 / 1 219",
        "tier": "4",
        "completions": "1"
      },
      {
        "map": "kz_village",
        "points": "185.7861",
        "time_record": "01:15.3282",
        "unixtime_record": 1753650466,
        "place_num": "298 / 23 438",
        "tier": "3",
        "completions": "8"
      },
      {
        "map": "kz_moorerutan",
        "points": "101.9947",
        "time_record": "03:04.8750",
        "unixtime_record": 1752759906,
        "place_num": "314 / 9 658",
        "tier": "2",
        "completions": "1"
      },
      {
        "map": "kz_slide_isnt_kz",
        "points": "67.6631",
        "time_record": "04:57.2969",
        "unixtime_record": 1771500624,
        "place_num": "342 / 637",
        "tier": "5",
        "completions": "5"
      },
      {
        "map": "kz_lmn",
        "points": "62.4436",
        "time_record": "00:57.0625",
        "unixtime_record": 1754392087,
        "place_num": "348 / 16 691",
        "tier": "1",
        "completions": "8"
      },
      {
        "map": "kz_maya",
        "points": "149.2104",
        "time_record": "03:43.1875",
        "unixtime_record": 1750369236,
        "place_num": "353 / 2 185",
        "tier": "3",
        "completions": "5"
      },
      {
        "map": "kz_illusion_gfix",
        "points": "114.2091",
        "time_record": "05:40.1094",
        "unixtime_record": 1752924356,
        "place_num": "366 / 2 136",
        "tier": "4",
        "completions": "3"
      },
      {
        "map": "kz_highland",
        "points": "105.5571",
        "time_record": "02:26.4375",
        "unixtime_record": 1752696178,
        "place_num": "388 / 9 284",
        "tier": "2",
        "completions": "8"
      },
      {
        "map": "kz_leto",
        "points": "118.9963",
        "time_record": "01:00.7500",
        "unixtime_record": 1780239756,
        "place_num": "392 / 118 461",
        "tier": "2",
        "completions": "31"
      },
      {
        "map": "kz_woodstock_v2",
        "points": "62.3892",
        "time_record": "01:26.3282",
        "unixtime_record": 1751811871,
        "place_num": "409 / 72 819",
        "tier": "1",
        "completions": "13"
      },
      {
        "map": "kz_variety_fix",
        "points": "217.0416",
        "time_record": "10:06.2344",
        "unixtime_record": 1770711517,
        "place_num": "411 / 29 541",
        "tier": "4",
        "completions": "100"
      },
      {
        "map": "kz_outback",
        "points": "154.5881",
        "time_record": "02:59.1875",
        "unixtime_record": 1767039822,
        "place_num": "421 / 12 835",
        "tier": "3",
        "completions": "4"
      },
      {
        "map": "kz_celestial",
        "points": "142.0600",
        "time_record": "01:20.3907",
        "unixtime_record": 1753664335,
        "place_num": "443 / 3 320",
        "tier": "3",
        "completions": "5"
      },
      {
        "map": "kz_obsidian",
        "points": "105.1742",
        "time_record": "10:20.9063",
        "unixtime_record": 1753133265,
        "place_num": "444 / 11 168",
        "tier": "2",
        "completions": "2"
      },
      {
        "map": "kz_haste",
        "points": "242.5487",
        "time_record": "01:56.3594",
        "unixtime_record": 1770905021,
        "place_num": "445 / 4 469",
        "tier": "4",
        "completions": "7"
      },
      {
        "map": "kz_checkmate",
        "points": "74.7045",
        "time_record": "08:56.8438",
        "unixtime_record": 1767037919,
        "place_num": "449 / 6 114",
        "tier": "2",
        "completions": "1"
      },
      {
        "map": "kz_victoria",
        "points": "60.6446",
        "time_record": "00:48.5000",
        "unixtime_record": 1751576147,
        "place_num": "462 / 60 063",
        "tier": "1",
        "completions": "35"
      },
      {
        "map": "kz_overworld_a2",
        "points": "77.7659",
        "time_record": "06:26.5313",
        "unixtime_record": 1752825681,
        "place_num": "468 / 3 523",
        "tier": "2",
        "completions": "2"
      },
      {
        "map": "kz_lumen",
        "points": "90.9249",
        "time_record": "03:00.1563",
        "unixtime_record": 1764858284,
        "place_num": "490 / 2 709",
        "tier": "3",
        "completions": "2"
      },
      {
        "map": "kz_dejavu",
        "points": "116.4492",
        "time_record": "09:17.4375",
        "unixtime_record": 1752940485,
        "place_num": "510 / 9 783",
        "tier": "3",
        "completions": "3"
      },
      {
        "map": "kz_edp445",
        "points": "112.9685",
        "time_record": "00:53.2188",
        "unixtime_record": 1753665008,
        "place_num": "517 / 18 912",
        "tier": "2",
        "completions": "6"
      },
      {
        "map": "kz_cf_slide",
        "points": "88.4869",
        "time_record": "01:38.2813",
        "unixtime_record": 1779986913,
        "place_num": "543 / 2 699",
        "tier": "3",
        "completions": "1"
      },
      {
        "map": "kz_phamous",
        "points": "125.4582",
        "time_record": "02:08.7657",
        "unixtime_record": 1746273805,
        "place_num": "568 / 195 867",
        "tier": "2",
        "completions": "23"
      },
      {
        "map": "kz_dzy_beyond_v2",
        "points": "112.7558",
        "time_record": "03:31.6719",
        "unixtime_record": 1751886915,
        "place_num": "577 / 18 624",
        "tier": "2",
        "completions": "7"
      },
      {
        "map": "kz_hb_smieszneznaczki",
        "points": "100.4749",
        "time_record": "04:42.8907",
        "unixtime_record": 1752819973,
        "place_num": "581 / 4 066",
        "tier": "3",
        "completions": "3"
      },
      {
        "map": "kz_gigablock_cs2",
        "points": "72.6274",
        "time_record": "06:48.1719",
        "unixtime_record": 1753247004,
        "place_num": "615 / 8 827",
        "tier": "2",
        "completions": "1"
      },
      {
        "map": "kz_mz",
        "points": "66.2508",
        "time_record": "00:12.0157",
        "unixtime_record": 1772192741,
        "place_num": "654 / 14 482",
        "tier": "1",
        "completions": "50"
      },
      {
        "map": "kz_lego",
        "points": "118.4530",
        "time_record": "01:21.3438",
        "unixtime_record": 1752867919,
        "place_num": "729 / 64 860",
        "tier": "2",
        "completions": "7"
      },
      {
        "map": "kz_echo",
        "points": "97.4512",
        "time_record": "01:28.7969",
        "unixtime_record": 1753015281,
        "place_num": "771 / 8 261",
        "tier": "2",
        "completions": "4"
      },
      {
        "map": "kz_breezeblocks",
        "points": "79.0146",
        "time_record": "03:21.2813",
        "unixtime_record": 1752720114,
        "place_num": "812 / 8 978",
        "tier": "2",
        "completions": "1"
      },
      {
        "map": "kz_hillside",
        "points": "55.2187",
        "time_record": "02:35.4219",
        "unixtime_record": 1752937553,
        "place_num": "886 / 21 031",
        "tier": "1",
        "completions": "3"
      },
      {
        "map": "kz_kiwiparadise",
        "points": "97.3189",
        "time_record": "00:43.2500",
        "unixtime_record": 1772896487,
        "place_num": "968 / 9 248",
        "tier": "2",
        "completions": "2"
      },
      {
        "map": "kz_summercliff2",
        "points": "89.2021",
        "time_record": "05:33.7344",
        "unixtime_record": 1754475561,
        "place_num": "1 505 / 15 237",
        "tier": "2",
        "completions": "2"
      },
      {
        "map": "kz_wetlands",
        "points": "95.1990",
        "time_record": "00:50.8594",
        "unixtime_record": 1752658432,
        "place_num": "1 899 / 15 917",
        "tier": "2",
        "completions": "22"
      }
    ]
  }
}